politsiyakat/__init__.py
politsiyakat/__main__.py
politsiyakat/.kdev4/politsiyakat.kdev4
politsiyakat/data/__init__.py
politsiyakat/data/__init__.pyc
politsiyakat/data/data_provider.py
politsiyakat/data/data_provider.pyc
politsiyakat/data/misc.py
politsiyakat/data/misc.pyc
politsiyakat/modules/__init__.py
politsiyakat/modules/__init__.pyc
politsiyakat/modules/flag_tasks.py
politsiyakat/modules/flag_tasks.pyc
politsiyakat/processing/__init__.py
politsiyakat/processing/__init__.pyc
politsiyakat/processing/async_pool.py
politsiyakat/processing/async_pool.pyc
politsiyakat-0.3.9.dist-info/DESCRIPTION.rst
politsiyakat-0.3.9.dist-info/METADATA
politsiyakat-0.3.9.dist-info/RECORD
politsiyakat-0.3.9.dist-info/WHEEL
politsiyakat-0.3.9.dist-info/metadata.json
politsiyakat-0.3.9.dist-info/top_level.txt
