Metadata-Version: 2.0
Name: politsiyakat
Version: 0.3.9
Summary: Tool to flag baselines with amplitude and phase problems
Home-page: https://github.com/bennahugo/politsiyakat
Author: Benjamin Hugo
Author-email: bhugo@ska.ac.za
License: GNU GPL v3
Download-URL: https://github.com/bennahugo/politsiyakat/archive/0.2alpha.tar.gz
Platform: UNKNOWN
Classifier: Development Status :: 3 - Alpha
Classifier: Intended Audience :: Science/Research
Classifier: License :: OSI Approved :: GNU General Public License v3 (GPLv3)
Classifier: Operating System :: OS Independent
Classifier: Programming Language :: Python
Classifier: Topic :: Software Development :: Libraries :: Python Modules
Classifier: Topic :: Scientific/Engineering :: Astronomy
Requires-Dist: futures
Requires-Dist: matplotlib (>=1.5.0)
Requires-Dist: numpy (>=1.13.3)
Requires-Dist: progress
Requires-Dist: python-casacore (>=2.1.2)
Requires-Dist: scipy (>=1.0.0)
